dataengine/__init__.py
dataengine/assets.py
dataengine/database.py
dataengine/dataset.py
dataengine/deploy_package_to_databricks.py
dataengine/engine.py
dataengine/query.py
dataengine/version.py
dataengine/utilities/__init__.py
dataengine/utilities/athena_utils.py
dataengine/utilities/databricks_utils.py
dataengine/utilities/datadog_utils.py
dataengine/utilities/general_utils.py
dataengine/utilities/github_utils.py
dataengine/utilities/glue_utils.py
dataengine/utilities/mysql_utils.py
dataengine/utilities/pandas_utils.py
dataengine/utilities/postgresql_utils.py
dataengine/utilities/redact_utils.py
dataengine/utilities/s3_utils.py
dataengine/utilities/slack_utils.py
dataengine/utilities/spark_utils.py
dataengine/utilities/data/aws_ec2_pricing.csv
dataengine/utilities/data/databricks_pricing.csv
dataengine-0.0.92.dist-info/licenses/LICENSE
tests/utilities/__init__.py
tests/utilities/test_athena_utils.py
tests/utilities/test_general_utils.py
tests/utilities/test_mysql_utils.py
tests/utilities/test_pandas_utils.py
tests/utilities/test_redact_utils.py
tests/utilities/test_s3_utils.py
dataengine-0.0.92.dist-info/METADATA
dataengine-0.0.92.dist-info/WHEEL
dataengine-0.0.92.dist-info/entry_points.txt
dataengine-0.0.92.dist-info/top_level.txt
dataengine-0.0.92.dist-info/RECORD
