Metadata-Version: 2.4
Name: dataengine
Version: 0.0.92
Summary: General purpose data engineering python package.
Home-page: https://github.com/leealessandrini/dataengine
Author: Daniel Lee Alessandrini
Author-email: alessandrinil@gmail.com
Classifier: Development Status :: 3 - Alpha
Classifier: Programming Language :: Python :: 3.9
Requires-Python: >=3.9
License-File: LICENSE
Requires-Dist: pytest
Requires-Dist: pytest-cov
Requires-Dist: PyYAML
Requires-Dist: numpy
Requires-Dist: pandas
Requires-Dist: pyarrow
Requires-Dist: moto
Requires-Dist: boto3
Requires-Dist: psycopg2-binary
Requires-Dist: PyMySQL
Requires-Dist: slack-sdk
Requires-Dist: tabulate
Requires-Dist: databricks-cli
Requires-Dist: PyGithub
Requires-Dist: scipy
Requires-Dist: marshmallow>=3.13.0
Requires-Dist: datadog_api_client
Requires-Dist: pyspark
Dynamic: author
Dynamic: author-email
Dynamic: classifier
Dynamic: description
Dynamic: home-page
Dynamic: license-file
Dynamic: requires-dist
Dynamic: requires-python
Dynamic: summary
